{
  "sorry": {
    "repo": {
      "remote": "https://github.com/teorth/pfr",
      "branch": "master",
      "commit": "49109e15a296831048024601c14d33399c526b38",
      "lean_version": "v4.19.0"
    },
    "location": {
      "path": "PFR/ApproxHomPFR.lean",
      "start_line": 181,
      "start_column": 65,
      "end_line": 181,
      "end_column": 70
    },
    "debug_info": {
      "goal": "G : Type u_1\ninst\u271d\u00b2 : AddCommGroup G\ninst\u271d\u00b9 : Fintype G\ninst\u271d : Module (ZMod 2) G\n\u22a2 Nat.card (G \u2192+ ZMod 2) = Nat.card G",
      "url": "https://github.com/teorth/pfr/blob/49109e15a296831048024601c14d33399c526b38/PFR/ApproxHomPFR.lean#L181"
    },
    "metadata": {
      "blame_email_hash": "d7f0e4a42bbb",
      "blame_date": "2025-05-01T23:21:54-07:00",
      "inclusion_date": "2025-06-01T03:03:10.481677+00:00"
    },
    "id": "0b0a333097173f6020e721a4295e35b9b92d2dec9e21abe2d182fd2bd4db8136"
  },
  "proof": "sorry",
  "proof_verified": false,
  "feedback": null,
  "verification_message": "Expected one less sorry in modified file",
  "success": true,
  "error_type": null,
  "error_message": null
}