[
  {
    "sorry": {
      "repo": {
        "remote": "https://github.com/leanprover-community/mathlib4",
        "branch": "MR_fae_WeakDeriv",
        "commit": "3553b46195d3457be68d016ea3b14b2aab5e53ad",
        "lean_version": "v4.27.0-rc1"
      },
      "location": {
        "path": "Mathlib/Analysis/Distribution/Distribution.lean",
        "start_line": 359,
        "start_column": 12,
        "end_line": 359,
        "end_column": 17
      },
      "debug_info": {
        "goal": "E : Type u_1\ninst‚úĚ¬Ļ¬≤ : NormedAddCommGroup E\ninst‚úĚ¬Ļ¬Ļ : NormedSpace ‚ĄĚ E\nő© : Opens E\nF : Type u_2\ninst‚úĚ¬Ļ‚Āį : AddCommGroup F\ninst‚úĚ‚ĀĻ : Module ‚ĄĚ F\ninst‚úĚ‚Āł : TopologicalSpace F\nF' : Type u_3\ninst‚úĚ‚Ā∑ : AddCommGroup F'\ninst‚úĚ‚Ā∂ : Module ‚ĄĚ F'\ninst‚úĚ‚ĀĶ : TopologicalSpace F'\nn k : ‚Ąē‚ąě\ninst‚úĚ‚Āī : IsTopologicalAddGroup F\ninst‚úĚ¬≥ : ContinuousSMul ‚ĄĚ F\ninst‚úĚ¬≤ : IsTopologicalAddGroup F'\ninst‚úĚ¬Ļ : ContinuousSMul ‚ĄĚ F'\ninst‚úĚ : FiniteDimensional ‚ĄĚ E\nT : @Distribution E inst‚úĚ¬Ļ¬≤ inst‚úĚ¬Ļ¬Ļ ő© F inst‚úĚ¬Ļ‚Āį inst‚úĚ‚ĀĻ inst‚úĚ‚Āł ‚ä§\n‚äĘ Continuous fun f =>\n    {\n      toFun := fun v =>\n        (@DFunLike.coe\n            (@Distribution E inst‚úĚ¬Ļ¬≤ inst‚úĚ¬Ļ¬Ļ ő© F inst‚úĚ¬Ļ‚Āį inst‚úĚ‚ĀĻ inst‚úĚ‚Āł ‚ä§ ‚ÜíL[‚ĄĚ]\n              @Distribution E inst‚úĚ¬Ļ¬≤ inst‚úĚ¬Ļ¬Ļ ő© F inst‚úĚ¬Ļ‚Āį inst‚úĚ‚ĀĻ inst‚úĚ‚Āł ‚ä§)\n            (@Distribution E inst‚úĚ¬Ļ¬≤ inst‚úĚ¬Ļ¬Ļ ő© F inst‚úĚ¬Ļ‚Āį inst‚úĚ‚ĀĻ inst‚úĚ‚Āł ‚ä§)\n            (fun x => @Distribution E inst‚úĚ¬Ļ¬≤ inst‚úĚ¬Ļ¬Ļ ő© F inst‚úĚ¬Ļ‚Āį inst‚úĚ‚ĀĻ inst‚úĚ‚Āł ‚ä§) ContinuousLinearMap.funLike\n            (@Distribution.lineDerivCLM E inst‚úĚ¬Ļ¬≤ inst‚úĚ¬Ļ¬Ļ ő© F inst‚úĚ¬Ļ‚Āį inst‚úĚ‚ĀĻ inst‚úĚ‚Āł inst‚úĚ‚Āī inst‚úĚ¬≥ v) T)\n          f,\n      map_add' := ‚čĮ, map_smul' := ‚čĮ, cont := ‚čĮ }",
        "url": "https://github.com/leanprover-community/mathlib4/blob/3553b46195d3457be68d016ea3b14b2aab5e53ad/Mathlib/Analysis/Distribution/Distribution.lean#L359"
      },
      "metadata": {
        "blame_email_hash": "0a3759cf16cc",
        "blame_date": "2025-12-10T18:42:45+01:00",
        "inclusion_date": "2026-01-10T16:31:03.661625+00:00"
      },
      "id": "03f101b704e12a56f82402a4d2c1426568621469d4a843c9f4411030f5b2953a"
    },
    "proof": null,
    "proof_verified": false,
    "feedback": null,
    "verification_message": "0 succeeded, 12 failed out of 12 attempts",
    "success": true,
    "error_type": null,
    "error_message": null,
    "strategy_name": "rfl_trivial_simp_simp_all_exact?_grind_ring_norm_num_omega_linarith_nlinarith_aesop_pass_at_1",
    "failed_attempts": [
      "rfl",
      "trivial",
      "simp",
      "simp_all",
      "exact?",
      "grind",
      "ring",
      "norm_num",
      "omega",
      "linarith",
      "nlinarith",
      "aesop"
    ],
    "successful_attempts": null,
    "input_tokens": 0,
    "output_tokens": 0,
    "estimated_cost": 0.0
  }
]